np_image_buffer/__init__.py
np_image_buffer/np_image_buffer.py
np_image_buffer-0.1.1.dist-info/AUTHORS.rst
np_image_buffer-0.1.1.dist-info/LICENSE
np_image_buffer-0.1.1.dist-info/METADATA
np_image_buffer-0.1.1.dist-info/WHEEL
np_image_buffer-0.1.1.dist-info/top_level.txt
np_image_buffer-0.1.1.dist-info/RECORD
