Metadata-Version: 2.1
Name: np-image-buffer
Version: 0.1.1
Summary: A NumPy circular buffer for fast image storing and indexing.
Home-page: https://github.com/jacopoabramo/np_image_buffer
Author: Jacopo Abramo
Author-email: jacopo.abramo@gmail.com
License: GNU General Public License v3
Keywords: np_image_buffer
Classifier: Development Status :: 2 - Pre-Alpha
Classifier: Intended Audience :: Developers
Classifier: License :: OSI Approved :: GNU General Public License v3 (GPLv3)
Classifier: Natural Language :: English
Classifier: Programming Language :: Python :: 3
Classifier: Programming Language :: Python :: 3.8
Classifier: Programming Language :: Python :: 3.9
Requires-Python: >=3.8
License-File: LICENSE
License-File: AUTHORS.rst
Requires-Dist: numpy
